crosslinker/__init__.py
crosslinker/lib.py
crosslinker/test.py
crosslinker-0.0.3.dist-info/LICENSE
crosslinker-0.0.3.dist-info/METADATA
crosslinker-0.0.3.dist-info/WHEEL
crosslinker-0.0.3.dist-info/top_level.txt
crosslinker-0.0.3.dist-info/RECORD
