Metadata-Version: 2.1
Name: crosslinker
Version: 0.0.3
Summary: CrossLinker: A Python Library for SEO - Friendly HTML Text Processing and Keyword Linking
Home-page: https://github.com/markolofsen/crosslinker
Author: Mark
Author-email: markolofsen@gmail.com
Classifier: Programming Language :: Python :: 3
Classifier: License :: OSI Approved :: MIT License
Classifier: Operating System :: OS Independent
Requires-Python: >=3.6
License-File: LICENSE
Requires-Dist: beautifulsoup4
Requires-Dist: nltk
